appins/__init__.py
appins/__main__.py
appins/main.py
appins/prompt_template.txt
appins-0.3.2.dist-info/entry_points.txt
appins-0.3.2.dist-info/LICENSE
appins-0.3.2.dist-info/WHEEL
appins-0.3.2.dist-info/METADATA
appins-0.3.2.dist-info/RECORD
