Metadata-Version: 2.1
Name: appins
Version: 0.3.2
Summary: appins - cli tool for enabledu ecosystem
Author-email: 0xsirsaif <sirsaif99@gmail.com>
Requires-Python: >=3.7
Classifier: License :: OSI Approved :: MIT License
Classifier: Development Status :: 4 - Beta
Classifier: Intended Audience :: Developers
Classifier: Programming Language :: Python :: 3.7
Classifier: Programming Language :: Python :: 3.8
Classifier: Programming Language :: Python :: 3.9
Classifier: Programming Language :: Python :: 3.10
Classifier: Programming Language :: Python :: 3 :: Only
Classifier: Topic :: Internet :: WWW/HTTP :: Session
Requires-Dist: typer >= 0.7.0
Requires-Dist: cookiecutter >= 2.1.1
Requires-Dist: torch >= 2.0.0
Requires-Dist: transformers >= 4.30.0
Requires-Dist: accelerate >= 0.20.0
Requires-Dist: colorama >= 0.4.6
Requires-Dist: flake8 ; extra == "dev"
Requires-Dist: pytest ; extra == "dev"
Requires-Dist: requests ; extra == "dev"
Requires-Dist: isort ; extra == "dev"
Requires-Dist: pytest-asyncio ; extra == "dev"
Requires-Dist: flake8-docstrings ; extra == "dev"
Requires-Dist: black ; extra == "dev"
Requires-Dist: mypy ; extra == "dev"
Requires-Dist: codecov ; extra == "dev"
Requires-Dist: pytest-cov ; extra == "dev"
Requires-Dist: pytest-mock ; extra == "dev"
Requires-Dist: asynctest ; extra == "dev"
Requires-Dist: flit ; extra == "dev"
Requires-Dist: bumpversion ; extra == "dev"
Project-URL: Documentation, https://github/0xsirsaif/appins
Provides-Extra: dev
